pyavalon/__init__.py
pyavalon/avalon/__init__.py
pyavalon/avalon/avalon.py
pyavalon/pdf/__init__.py
pyavalon/pdf/fonts/IIIF Prezi3 Classes - Sheet1.csv
pyavalon/pdf/fonts/OFL.txt
pyavalon/pdf/fonts/Oswald-VariableFont_wght.ttf
pyavalon/pdf/fonts/Oswald.zip
pyavalon/pdf/fonts/README.txt
pyavalon/pdf/fonts/crimson/Crimson_Text/CrimsonText-Bold.ttf
pyavalon/pdf/fonts/crimson/Crimson_Text/CrimsonText-BoldItalic.ttf
pyavalon/pdf/fonts/crimson/Crimson_Text/CrimsonText-Italic.ttf
pyavalon/pdf/fonts/crimson/Crimson_Text/CrimsonText-Regular.ttf
pyavalon/pdf/fonts/crimson/Crimson_Text/CrimsonText-SemiBold.ttf
pyavalon/pdf/fonts/crimson/Crimson_Text/CrimsonText-SemiBoldItalic.ttf
pyavalon/pdf/fonts/crimson/Crimson_Text/OFL.txt
"pyavalon/pdf/fonts/crimson/Crimson_Text,Work_Sans.zip"
pyavalon/pdf/fonts/crimson/Work_Sans/OFL.txt
pyavalon/pdf/fonts/crimson/Work_Sans/README.txt
pyavalon/pdf/fonts/crimson/Work_Sans/WorkSans-Italic-VariableFont_wght.ttf
pyavalon/pdf/fonts/crimson/Work_Sans/WorkSans-VariableFont_wght.ttf
pyavalon/pdf/fonts/crimson/Work_Sans/static/WorkSans-Black.ttf
pyavalon/pdf/fonts/crimson/Work_Sans/static/WorkSans-BlackItalic.ttf
pyavalon/pdf/fonts/crimson/Work_Sans/static/WorkSans-Bold.ttf
pyavalon/pdf/fonts/crimson/Work_Sans/static/WorkSans-BoldItalic.ttf
pyavalon/pdf/fonts/crimson/Work_Sans/static/WorkSans-ExtraBold.ttf
pyavalon/pdf/fonts/crimson/Work_Sans/static/WorkSans-ExtraBoldItalic.ttf
pyavalon/pdf/fonts/crimson/Work_Sans/static/WorkSans-ExtraLight.ttf
pyavalon/pdf/fonts/crimson/Work_Sans/static/WorkSans-ExtraLightItalic.ttf
pyavalon/pdf/fonts/crimson/Work_Sans/static/WorkSans-Italic.ttf
pyavalon/pdf/fonts/crimson/Work_Sans/static/WorkSans-Light.ttf
pyavalon/pdf/fonts/crimson/Work_Sans/static/WorkSans-LightItalic.ttf
pyavalon/pdf/fonts/crimson/Work_Sans/static/WorkSans-Medium.ttf
pyavalon/pdf/fonts/crimson/Work_Sans/static/WorkSans-MediumItalic.ttf
pyavalon/pdf/fonts/crimson/Work_Sans/static/WorkSans-Regular.ttf
pyavalon-0.1.12.dist-info/METADATA
pyavalon-0.1.12.dist-info/WHEEL
pyavalon-0.1.12.dist-info/entry_points.txt
pyavalon-0.1.12.dist-info/RECORD
