Metadata-Version: 2.1
Name: pyavalon
Version: 0.1.12
Summary: 
Author: Mark Baggett
Author-email: markpbaggett@gmail.com
Requires-Python: >=3.12,<4.0
Classifier: Programming Language :: Python :: 3
Classifier: Programming Language :: Python :: 3.12
Requires-Dist: click (>=8.2.1,<9.0.0)
Requires-Dist: fpdf (>=1.7.2,<2.0.0)
Requires-Dist: iiif-prezi3 (>=3.0.0,<4.0.0)
Requires-Dist: pytest (>=8.4.2,<9.0.0)
Requires-Dist: requests (>=2.32.4,<3.0.0)
Requires-Dist: ruff (>=0.12.11,<0.13.0)
Requires-Dist: tqdm (>=4.67.1,<5.0.0)
Requires-Dist: weasyprint (>=66.0,<67.0)
Requires-Dist: webvtt-py (>=0.5.1,<0.6.0)
